dagster_duckdb_polars/__init__.py
dagster_duckdb_polars/duckdb_polars_type_handler.py
dagster_duckdb_polars/py.typed
dagster_duckdb_polars/version.py
dagster_duckdb_polars-0.28.13.dist-info/licenses/LICENSE
dagster_duckdb_polars-0.28.13.dist-info/METADATA
dagster_duckdb_polars-0.28.13.dist-info/WHEEL
dagster_duckdb_polars-0.28.13.dist-info/top_level.txt
dagster_duckdb_polars-0.28.13.dist-info/RECORD
