Metadata-Version: 2.4
Name: dagster-duckdb-polars
Version: 0.28.13
Summary: Package for storing Polars DataFrames in DuckDB.
Home-page: https://github.com/dagster-io/dagster/tree/master/python_modules/libraries/dagster-duckdb-polars
Author: Dagster Labs
Author-email: hello@dagsterlabs.com
License: Apache-2.0
Classifier: Programming Language :: Python :: 3.10
Classifier: Programming Language :: Python :: 3.11
Classifier: License :: OSI Approved :: Apache Software License
Classifier: Operating System :: OS Independent
Requires-Python: >=3.10,<3.15
License-File: LICENSE
Requires-Dist: dagster==1.12.13
Requires-Dist: dagster-duckdb==0.28.13
Requires-Dist: polars[pyarrow]
Dynamic: author
Dynamic: author-email
Dynamic: classifier
Dynamic: home-page
Dynamic: license
Dynamic: license-file
Dynamic: requires-dist
Dynamic: requires-python
Dynamic: summary
